django_lexorank/__init__.py
django_lexorank/admin/__init__.py
django_lexorank/admin/ranked_model.py
django_lexorank/admin/scheduled_rebalancing.py
django_lexorank/apps.py
django_lexorank/fields.py
django_lexorank/lexorank.py
django_lexorank/managers.py
django_lexorank/migrations/0001_initial.py
django_lexorank/migrations/__init__.py
django_lexorank/models/__init__.py
django_lexorank/models/ranked_model.py
django_lexorank/models/scheduled_rebalancing.py
django_lexorank-0.1.4.dist-info/LICENSE
django_lexorank-0.1.4.dist-info/METADATA
django_lexorank-0.1.4.dist-info/WHEEL
django_lexorank-0.1.4.dist-info/RECORD
