Metadata-Version: 2.3
Name: django-lexorank
Version: 0.1.4
Summary: This package implements an algorithm similar to JIRA's lexorank, but without using buckets for rebalancing that can be used with Django projects.
License: MIT
Author: Alex Rozum
Author-email: rozumalex@gmail.com
Requires-Python: >=3.8,<4.0
Classifier: Development Status :: 4 - Beta
Classifier: Environment :: Web Environment
Classifier: Framework :: Django
Classifier: Intended Audience :: Developers
Classifier: License :: OSI Approved :: MIT License
Classifier: Operating System :: OS Independent
Classifier: Programming Language :: Python :: 3
Classifier: Programming Language :: Python :: 3.8
Classifier: Programming Language :: Python :: 3.9
Classifier: Programming Language :: Python :: 3.10
Classifier: Programming Language :: Python :: 3.11
Classifier: Programming Language :: Python :: 3.12
Classifier: Programming Language :: Python :: 3.13
Classifier: Topic :: Software Development :: Libraries :: Python Modules
Requires-Dist: django (>=3.2)
Project-URL: Bug Tracker, https://github.com/rozumdev/django-lexorank/issues/
Project-URL: Homepage, https://github.com/rozumdev/django-lexorank/
